tess_coadds/__init__.py
tess_coadds-1.0.0.dist-info/METADATA
tess_coadds-1.0.0.dist-info/WHEEL
tess_coadds-1.0.0.dist-info/top_level.txt
tess_coadds-1.0.0.dist-info/RECORD
